[{"title":"Google Chrome browser privacy plan investigated in UK","url":"https:\/\/www.bbc.co.uk\/news\/technology-55219750"},{"title":"Covid-19: Government denies 'snubbing' BT's wi-fi for pupils offer","url":"https:\/\/www.bbc.co.uk\/news\/uk-politics-55588748"},{"title":"David Attenborough won't return to Instagram","url":"https:\/\/www.bbc.co.uk\/news\/newsbeat-55586840"},{"title":"Fifa 21 and Frozen 2 top digital sales of 2020","url":"https:\/\/www.bbc.co.uk\/news\/technology-55588094"},{"title":"Trump allowed back onto Twitter","url":"https:\/\/www.bbc.co.uk\/news\/technology-55569604"},{"title":"'Litany of failures' on road to 1Gbps, MPs warn","url":"https:\/\/www.bbc.co.uk\/news\/technology-55573804"},{"title":"Elon Musk becomes world's richest person as wealth tops $185bn","url":"https:\/\/www.bbc.co.uk\/news\/technology-55578403"},{"title":"Hyundai's confusion over Apple electric car tie-up","url":"https:\/\/www.bbc.co.uk\/news\/business-55583504"},{"title":"WhatsApp and Facebook to share users' data outside Europe and UK","url":"https:\/\/www.bbc.co.uk\/news\/technology-55573149"},{"title":"Facial recognition identifies people wearing masks","url":"https:\/\/www.bbc.co.uk\/news\/technology-55573802"},{"title":"Fears schools will be overwhelmed by laptopless pupils","url":"https:\/\/www.bbc.co.uk\/news\/education-55565537"},{"title":"AI draws dog-walking baby radish in a tutu","url":"https:\/\/www.bbc.co.uk\/news\/technology-55559463"},{"title":"The robot made of ice and other tech news","url":"https:\/\/www.bbc.co.uk\/news\/technology-55574902"},{"title":"The many adventures of Elon Musk, the world's richest person","url":"https:\/\/www.bbc.co.uk\/news\/business-45645422"},{"title":"Adobe Flash Player reaches the end of its life","url":"https:\/\/www.bbc.co.uk\/news\/technology-55501198"},{"title":"Moscow train carriage helps rehome stray pets","url":"https:\/\/www.bbc.co.uk\/news\/world-europe-55418334"},{"title":"Hogmanay drone swarm lights up Scottish skies","url":"https:\/\/www.bbc.co.uk\/news\/uk-scotland-55492620"},{"title":"Donald Trump\u2019s Twitter endgame","url":"https:\/\/www.bbc.co.uk\/news\/technology-55571291"},{"title":"Greener planes of the future... or just pretty plans?","url":"https:\/\/www.bbc.co.uk\/news\/business-51751984"},{"title":"Home-schooling: How to help your child\u2019s online learning","url":"https:\/\/www.bbc.co.uk\/news\/technology-55549072"},{"title":"Elon Musk's six secrets to business success","url":"https:\/\/www.bbc.co.uk\/news\/business-55554343"},{"title":"Vikkstar on his plans for growing Call of Duty esports","url":"https:\/\/www.bbc.co.uk\/news\/newsbeat-55553453"},{"title":"Covid travel: Why Instagram is still full of celebrities 'on holiday'","url":"https:\/\/www.bbc.co.uk\/news\/world-55546760"}]